{
  "version": 1,
  "license": "CC-BY-SA-3.0",
  "copyright": "Taken from https://github.com/Skyrat-SS13/Skyrat13/blob/22c8cd930c4dedab170f588874384e0497176d41/modular_skyrat/icons/mob/synthliz/synthliz_body_markings.dmi, modifed by Github KittenColony / Discord kittencolony (297865728374210561)",
  "size": {
    "x": 32,
    "y": 32
  },
  "states": [
    {
      "name": "body_scute",
      "directions": 4
    },
    {
      "name": "body_plate",
      "directions": 4
    },
    {
      "name": "body_pecs_primary",
      "directions": 4
    },
    {
      "name": "body_pecs_secondary",
      "directions": 4
    },
    {
      "name": "body_lights_primary",
      "directions": 4
    },
    {
      "name": "body_lights_secondary",
      "directions": 4
    }
  ]
}