{
    "version": 1,
    "license": "CC-BY-SA-4.0",
    "copyright": "BeeRobynn, plyush, bellcatsu , George Gimme, Ahti, and dootythefrooty, plushie_nuke taken from tgstation at https://github.com/tgstation/tgstation/commit/e1142f20f5e4661cb6845cfcf2dd69f864d67432",
    "size": {
        "x": 32,
        "y": 32
    },
    "states": [
        {
            "name": "plushie_louie"
        },
        {
            "name": "plushie_durk"
        },
        {
            "name": "plushie_blackburn"
        },
        {
            "name": "plushie_matryoskya"
        },
        {
            "name": "plushie_kobliska"
        },
        {
            "name": "plushie_desislava",
            "delays": [
                [
                    0.5,
                    0.25
                ]
            ]
        },
        {
            "name": "bingleing"
        },
        {
            "name": "bongle",
            "directions": 4
        },
        {
            "name": "bingle_pony",
            "directions": 4
        },
        {
            "name": "plushie_nuke"
        },
        {
            "name": "plushienukie-inhand-left",
            "directions": 4
        },
        {
            "name": "plushienukie-inhand-right",
            "directions": 4
        }
    ]
}
